hr_dataset/__init__.py
hr_dataset/class_functions/__init__.py
hr_dataset/class_functions/load_dataset.py
hr_dataset/config/config_parser.py
hr_dataset/config/validate_inputs.py
hr_dataset/differenceregel/differenceregel.py
hr_dataset/functions/__init__.py
hr_dataset/functions/file_handler.py
hr_dataset/functions/some_answers.py
hr_dataset/module.py
hr_dataset/resultatoversigt/__init__.py
hr_dataset/resultatoversigt/resultatoversigt.py
hr_dataset-0.1.5.dist-info/METADATA
hr_dataset-0.1.5.dist-info/WHEEL
hr_dataset-0.1.5.dist-info/RECORD
