Metadata-Version: 2.1
Name: hr-dataset
Version: 0.1.5
Summary: 
Author: Christian Frost
Author-email: terminated@ramboll.com
Requires-Python: >=3.12,<4.0
Classifier: Programming Language :: Python :: 3
Classifier: Programming Language :: Python :: 3.12
Requires-Dist: ipykernel (>=6.29.3,<7.0.0)
Requires-Dist: loguru (>=0.7.2,<0.8.0)
Requires-Dist: openpyxl (>=3.1.2,<4.0.0)
Requires-Dist: pandas (>=2.2.1,<3.0.0)
